datagovgr_datamodels/API-DOC-VERSION
datagovgr_datamodels/__init__.py
datagovgr_datamodels/py.typed
datagovgr_datamodels/pydantic_v1/__init__.py
datagovgr_datamodels/pydantic_v1/models.py
datagovgr_datamodels/pydantic_v2/__init__.py
datagovgr_datamodels/pydantic_v2/models.py
datagovgr_datamodels-0.1.0a1.dist-info/LICENSE
datagovgr_datamodels-0.1.0a1.dist-info/METADATA
datagovgr_datamodels-0.1.0a1.dist-info/WHEEL
datagovgr_datamodels-0.1.0a1.dist-info/RECORD
