Metadata-Version: 2.1
Name: datagovgr-datamodels
Version: 0.1.0a1
Summary: Datamodels generated from the data.gov.gr OpenAPI documentation
Home-page: https://github.com/KAUTH/govgr-opendata-api-schema/blob/main/datamodels/python
License: MIT
Keywords: gov-gr,datamodels,open-data
Author: Konstantinos Papadopoulos
Author-email: konpap1996@yahoo.com
Requires-Python: >=3.7,<4.0
Classifier: License :: OSI Approved :: MIT License
Classifier: Natural Language :: English
Classifier: Operating System :: OS Independent
Classifier: Programming Language :: Python
Classifier: Programming Language :: Python :: 3
Classifier: Programming Language :: Python :: 3.7
Classifier: Programming Language :: Python :: 3.8
Classifier: Programming Language :: Python :: 3.9
Classifier: Programming Language :: Python :: 3.10
Classifier: Programming Language :: Python :: 3.11
Classifier: Programming Language :: Python :: 3.11 
Classifier: Programming Language :: Python :: 3.12 
Classifier: Programming Language :: Python :: Implementation :: PyPy
Classifier: Topic :: Software Development
Provides-Extra: pydantic
Project-URL: Documentation, https://github.com/KAUTH/govgr-opendata-api-schema/blob/main/datamodels/python/README.md
Project-URL: Repository, https://github.com/KAUTH/govgr-opendata-api-schema
